agraph_utils/__init__.py
agraph_utils/buffer_triples.py
agraph_utils/geospatial.py
agraph_utils/utilities.py
agraph_utils/vector_search.py
tests/__init__.py
tests/test_buffer_triples.py
tests/test_geospatial.py
tests/test_utilities.py
tests/test_vector_search.py
agraph_utils-0.5.dist-info/METADATA
agraph_utils-0.5.dist-info/WHEEL
agraph_utils-0.5.dist-info/top_level.txt
agraph_utils-0.5.dist-info/RECORD
