Metadata-Version: 2.1
Name: agraph_utils
Version: 0.5
Summary: A set of utilities for working with AllegroGraph
Home-page: https://github.com/hansaasman/agraph_utils
Author: Hans Aasman
Author-email: hansaasman@gmail.com
Classifier: Programming Language :: Python :: 3
Classifier: Operating System :: OS Independent
Requires-Dist: agraph-python
Requires-Dist: pandas
